jytest0.py
jytestrunopt0-0.0.2.dist-info/METADATA
jytestrunopt0-0.0.2.dist-info/WHEEL
jytestrunopt0-0.0.2.dist-info/top_level.txt
jytestrunopt0-0.0.2.dist-info/RECORD
