Metadata-Version: 2.1
Name: jytestrunopt0
Version: 0.0.2
Summary: opt0
Home-page: https://www.cnblogs.com/zhangjialu2015/p/5173313.html
Author: zjy
Author-email: unknown@bgsn.com
License: UNKNOWN
Platform: UNKNOWN
Provides-Extra: a
Requires-Dist: jytestrunopt1 (==0.0.1) ; extra == 'a'
Provides-Extra: b
Requires-Dist: jytestrunopt2 (==0.0.1) ; extra == 'b'
